mtconnect/__init__.py
mtconnect/agent.py
mtconnect/device.py
mtconnect/error.py
mtconnect/helper.py
mtconnect/loghandler.py
mtconnect/response.py
mtconnect/standard_list.py
mtconnect/storage.py
mtconnect/xmlhelper.py
mtconnect-0.3.3.dist-info/LICENSE
mtconnect-0.3.3.dist-info/METADATA
mtconnect-0.3.3.dist-info/WHEEL
mtconnect-0.3.3.dist-info/RECORD
